ip_reveal_headless/.idea/.gitignore
ip_reveal_headless/.idea/inspectionProfiles/profiles_settings.xml
ip_reveal_headless/.idea/ip_reveal.iml
ip_reveal_headless/.idea/misc.xml
ip_reveal_headless/.idea/modules.xml
ip_reveal_headless/.idea/vcs.xml
ip_reveal_headless/__init__.py
ip_reveal_headless/config/__init__.py
ip_reveal_headless/config/arguments/__init__.py
ip_reveal_headless/config/default_config.ini
ip_reveal_headless/config/developer.py
ip_reveal_headless/config/errors.py
ip_reveal_headless/config/paths.ini
ip_reveal_headless/log_engine/__init__.py
ip_reveal_headless/tools/__init__.py
ip_reveal_headless/tools/arguments/__init__.py
ip_reveal_headless/version/__init__.py
ip_reveal_headless/version/VERSION.txt
ip_reveal_headless-1.1.2.dist-info/entry_points.txt
ip_reveal_headless-1.1.2.dist-info/LICENSE
ip_reveal_headless-1.1.2.dist-info/METADATA
ip_reveal_headless-1.1.2.dist-info/WHEEL
ip_reveal_headless-1.1.2.dist-info/RECORD
