Metadata-Version: 2.1
Name: ip-reveal-headless
Version: 1.1.2
Summary: Quickly ascertain your public IP address, hostname, and local IP address.
License: MIT
Author: Taylor B.
Author-email: tayjaybabee@gmail.com
Requires-Python: >=3.10,<4.0
Classifier: License :: OSI Approved :: MIT License
Classifier: Programming Language :: Python :: 3
Classifier: Programming Language :: Python :: 3.10
Classifier: Programming Language :: Python :: 3.11
Classifier: Programming Language :: Python :: 3.12
Requires-Dist: humanize (>=4.9.0,<5.0.0)
Requires-Dist: inspy_logger (>=3.2.0,<4.0.0)
Requires-Dist: inspyre-toolbox (>=1.5.3,<2.0.0)
Requires-Dist: inspyred_print (>=1.0,<2.0)
Requires-Dist: johnnydep (>=1.10,<2.0)
Requires-Dist: pypattyrn (>=1.2,<2.0)
Requires-Dist: requests (>=2.32.3,<3.0.0)
Requires-Dist: toml (>=0.10.2,<0.11.0)
Requires-Dist: urllib3 (>=2.2.2,<3.0.0)
